kigadgets/__init__.py
kigadgets/__main__.py
kigadgets/board.py
kigadgets/drawing.py
kigadgets/environment.py
kigadgets/exceptions.py
kigadgets/item.py
kigadgets/layer.py
kigadgets/module.py
kigadgets/pad.py
kigadgets/point.py
kigadgets/size.py
kigadgets/track.py
kigadgets/units.py
kigadgets/util.py
kigadgets/via.py
kigadgets/zone.py
kigadgets-0.5.1.dist-info/LICENSE
kigadgets-0.5.1.dist-info/METADATA
kigadgets-0.5.1.dist-info/WHEEL
kigadgets-0.5.1.dist-info/top_level.txt
kigadgets-0.5.1.dist-info/RECORD
