Metadata-Version: 2.2
Name: kigadgets
Version: 0.5.1
Summary: Cross-version python wrapper for KiCad pcbnew
Home-page: https://github.com/atait/kicad-python/
Author: Piers Titus van der Torren, Miguel Angel Ajo, Hasan Yavuz Ozderya, Alex Tait
Author-email: atait@ieee.org
License: GPL v2
License-File: LICENSE
Dynamic: author
Dynamic: author-email
Dynamic: description
Dynamic: description-content-type
Dynamic: home-page
Dynamic: license
Dynamic: summary
